dpy_init
