Metadata-Version: 2.1
Name: dpy-init
Version: 1.0.10
License-File: LICENSE
Requires-Dist: click
